{
  "0":{
    "#":0,
    "Country\/Other":0,
    "Total Cases":"721",
    "New Cases":0,
    "Total Deaths":"15",
    "New Deaths":0,
    "Total Recovered":"651",
    "New Recovered":0,
    "Active Cases":"55",
    "Serious\/Critical":"4",
    "Tot Cases\/ 1M pop":0,
    "Deaths\/ 1M pop":0,
    "Total Tests":0,
    "Tests\/  1M pop ":0,
    "Population":0,
    "Continent":0,
    "1 Case every X ppl":0,
    "1 Death every X ppl":0,
    "1 Test every X ppl":0
  },
  "1":{
    "#":0,
    "Country\/Other":"Africa",
    "Total Cases":"164,608",
    "New Cases":"+4,770",
    "Total Deaths":"4,626",
    "New Deaths":"+106",
    "Total Recovered":"72,291",
    "New Recovered":"+3,306",
    "Active Cases":"87,691",
    "Serious\/Critical":"435",
    "Tot Cases\/ 1M pop":0,
    "Deaths\/ 1M pop":0,
    "Total Tests":0,
    "Tests\/  1M pop ":0,
    "Population":0,
    "Continent":"Africa",
    "1 Case every X ppl":0,
    "1 Death every X ppl":0,
    "1 Test every X ppl":0
  },
  "2":{
    "#":0,
    "Country\/Other":"Asia",
    "Total Cases":"1,226,555",
    "New Cases":"+32,328",
    "Total Deaths":"32,459",
    "New Deaths":"+628",
    "Total Recovered":"748,387",
    "New Recovered":"+17,497",
    "Active Cases":"445,709",
    "Serious\/Critical":"14,514",
    "Tot Cases\/ 1M pop":0,
    "Deaths\/ 1M pop":0,
    "Total Tests":0,
    "Tests\/  1M pop ":0,
    "Population":0,
    "Continent":"Asia",
    "1 Case every X ppl":0,
    "1 Death every X ppl":0,
    "1 Test every X ppl":0
  },
  "3":{
    "#":0,
    "Country\/Other":"Europe",
    "Total Cases":"2,028,178",
    "New Cases":"+17,029",
    "Total Deaths":"176,445",
    "New Deaths":"+888",
    "Total Recovered":"1,027,853",
    "New Recovered":"+14,799",
    "Active Cases":"823,880",
    "Serious\/Critical":"8,538",
    "Tot Cases\/ 1M pop":0,
    "Deaths\/ 1M pop":0,
    "Total Tests":0,
    "Tests\/  1M pop ":0,
    "Population":0,
    "Continent":"Europe",
    "1 Case every X ppl":0,
    "1 Death every X ppl":0,
    "1 Test every X ppl":0
  },
  "4":{
    "#":0,
    "Country\/Other":"North America",
    "Total Cases":"2,143,405",
    "New Cases":"+22,619",
    "Total Deaths":"128,676",
    "New Deaths":"+1,522",
    "Total Recovered":"800,890",
    "New Recovered":"+9,756",
    "Active Cases":"1,213,839",
    "Serious\/Critical":"19,286",
    "Tot Cases\/ 1M pop":0,
    "Deaths\/ 1M pop":0,
    "Total Tests":0,
    "Tests\/  1M pop ":0,
    "Population":0,
    "Continent":"North America",
    "1 Case every X ppl":0,
    "1 Death every X ppl":0,
    "1 Test every X ppl":0
  },
  "5":{
    "#":0,
    "Country\/Other":"Oceania",
    "Total Cases":"8,839",
    "New Cases":"+8",
    "Total Deaths":"124",
    "New Deaths":0,
    "Total Recovered":"8,222",
    "New Recovered":"+14",
    "Active Cases":"493",
    "Serious\/Critical":"5",
    "Tot Cases\/ 1M pop":0,
    "Deaths\/ 1M pop":0,
    "Total Tests":0,
    "Tests\/  1M pop ":0,
    "Population":0,
    "Continent":"Australia\/Oceania",
    "1 Case every X ppl":0,
    "1 Death every X ppl":0,
    "1 Test every X ppl":0
  },
  "6":{
    "#":0,
    "Country\/Other":"South America",
    "Total Cases":"959,305",
    "New Cases":"+13,575",
    "Total Deaths":"43,045",
    "New Deaths":"+387",
    "Total Recovered":"452,299",
    "New Recovered":"+57,640",
    "Active Cases":"463,961",
    "Serious\/Critical":"11,404",
    "Tot Cases\/ 1M pop":0,
    "Deaths\/ 1M pop":0,
    "Total Tests":0,
    "Tests\/  1M pop ":0,
    "Population":0,
    "Continent":"South America",
    "1 Case every X ppl":0,
    "1 Death every X ppl":0,
    "1 Test every X ppl":0
  },
  "7":{
    "#":"1",
    "Country\/Other":"USA",
    "Total Cases":"1,898,194",
    "New Cases":"+16,989",
    "Total Deaths":"108,989",
    "New Deaths":"+930",
    "Total Recovered":"651,985",
    "New Recovered":"+6,011",
    "Active Cases":"1,137,220",
    "Serious\/Critical":"16,921",
    "Tot Cases\/ 1M pop":"5,737",
    "Deaths\/ 1M pop":"329",
    "Total Tests":"19,002,119",
    "Tests\/  1M pop ":"57,434",
    "Population":"330,854,064",
    "Continent":"North America",
    "1 Case every X ppl":"174",
    "1 Death every X ppl":"3,036",
    "1 Test every X ppl":"17"
  },
  "8":{
    "#":0,
    "Country\/Other":"World",
    "Total Cases":"6,531,611",
    "New Cases":"+90,329",
    "Total Deaths":"385,390",
    "New Deaths":"+3,531",
    "Total Recovered":"3,110,593",
    "New Recovered":"+103,012",
    "Active Cases":"3,035,628",
    "Serious\/Critical":"54,186",
    "Tot Cases\/ 1M pop":"838",
    "Deaths\/ 1M pop":"49.4",
    "Total Tests":0,
    "Tests\/  1M pop ":0,
    "Population":0,
    "Continent":"All",
    "1 Case every X ppl":0,
    "1 Death every X ppl":0,
    "1 Test every X ppl":0
  }
}